xpression_tk-0.2.3.dist-info/licenses/LICENSE
xtk/__init__.py
xtk/__main__.py
xtk/cli.py
xtk/explainer.py
xtk/fluent_api.py
xtk/llm_inferrer.py
xtk/parser.py
xtk/py.typed
xtk/rewriter.py
xtk/rule_dsl.py
xtk/rule_loader.py
xtk/rule_utils.py
xtk/step_logger.py
xtk/rules/__init__.py
xtk/rules/algebra.rules
xtk/rules/algebra_rules.py
xtk/rules/algebra_rules_rich.py
xtk/rules/arithmetic_rules.py
xtk/rules/deriv.rules
xtk/rules/deriv_rules.py
xtk/rules/deriv_rules_rich.py
xtk/rules/exp-log.py
xtk/rules/integral-rules.py
xtk/rules/limit-rules.py
xtk/rules/primitives.py
xtk/rules/trig-rules.py
xpression_tk-0.2.3.dist-info/METADATA
xpression_tk-0.2.3.dist-info/WHEEL
xpression_tk-0.2.3.dist-info/entry_points.txt
xpression_tk-0.2.3.dist-info/top_level.txt
xpression_tk-0.2.3.dist-info/RECORD
