Metadata-Version: 2.4
Name: xpression-tk
Version: 0.2.3
Summary: A powerful symbolic expression toolkit for rule-based term rewriting
Author-email: Alex Towell <lex@metafunctor.com>
License-Expression: MIT
Project-URL: Homepage, https://github.com/queelius/xtk
Project-URL: Documentation, https://github.com/queelius/xtk#readme
Project-URL: Repository, https://github.com/queelius/xtk.git
Project-URL: Issues, https://github.com/queelius/xtk/issues
Keywords: symbolic,computation,rewriting,pattern-matching,algebra,calculus
Classifier: Development Status :: 4 - Beta
Classifier: Intended Audience :: Developers
Classifier: Intended Audience :: Science/Research
Classifier: Operating System :: OS Independent
Classifier: Programming Language :: Python :: 3
Classifier: Programming Language :: Python :: 3.8
Classifier: Programming Language :: Python :: 3.9
Classifier: Programming Language :: Python :: 3.10
Classifier: Programming Language :: Python :: 3.11
Classifier: Programming Language :: Python :: 3.12
Classifier: Topic :: Scientific/Engineering :: Mathematics
Classifier: Topic :: Software Development :: Libraries :: Python Modules
Requires-Python: >=3.8
License-File: LICENSE
Requires-Dist: rich>=13.0
Provides-Extra: dev
Requires-Dist: pytest>=7.0; extra == "dev"
Requires-Dist: pytest-cov>=4.0; extra == "dev"
Requires-Dist: black>=23.0; extra == "dev"
Requires-Dist: flake8>=6.0; extra == "dev"
Requires-Dist: mypy>=1.0; extra == "dev"
Requires-Dist: isort>=5.0; extra == "dev"
Provides-Extra: docs
Requires-Dist: sphinx>=5.0; extra == "docs"
Requires-Dist: sphinx-rtd-theme>=1.0; extra == "docs"
Dynamic: license-file
